{"categories": [{"name": "incorrect", "value": 80, "percent": 15.0, "fill": "#E74C3C"}, {"name": "partially incorrect", "value": 366, "percent": 67.0, "fill": "#F39C12"}, {"name": "ambiguous", "value": 26, "percent": 5.0, "fill": "#512E5F"}, {"name": "partially correct", "value": 21, "percent": 4.0, "fill": "#82E0AA"}, {"name": "correct", "value": 56, "percent": 10.0, "fill": "#28B463"}], "cumulative_category": [{"name": "3 Workers", "correct & partially correct": 0, "correct": 0, "partially correct": 0, "ambiguous": 0, "partially incorrect": 0, "incorrect": 0, "incorrect & partially incorrect": 80}, {"name": "2 Workers", "correct & partially correct": 0, "correct": 0, "partially correct": 0, "ambiguous": 0, "partially incorrect": 183, "incorrect": 0, "incorrect & partially incorrect": 183}, {"name": "1 Worker", "correct & partially correct": 77, "correct": 56, "partially correct": 21, "ambiguous": 26, "partially incorrect": 183, "incorrect": 80, "incorrect & partially incorrect": 183}, {"name": "Total", "correct & partially correct": 183, "correct": 183, "partially correct": 183, "ambiguous": 183, "partially incorrect": 183, "incorrect": 183, "incorrect & partially incorrect": 183}], "topics": [{"name": "object recognition", "value": 73, "percent": 39.89, "fill": "#F06292"}, {"name": "attribute classification", "value": 53, "percent": 28.96, "fill": "#4FC3F7"}, {"name": "counting", "value": 24, "percent": 13.11, "fill": "#AED581"}, {"name": "spatial", "value": 15, "percent": 8.2, "fill": "#FF8A65"}, {"name": "action recognition", "value": 15, "percent": 8.2, "fill": "#BA68C8"}, {"name": "comparative", "value": 2, "percent": 1.09, "fill": "#4DB6AC"}, {"name": "reasoning", "value": 1, "percent": 0.55, "fill": "#FFF176"}], "answer_list": [{"name": "yes", "value": 26, "percent": 18.31}, {"name": "2", "value": 9, "percent": 6.34}, {"name": "red", "value": 8, "percent": 5.63}, {"name": "standing", "value": 7, "percent": 4.93}, {"name": "purple", "value": 7, "percent": 4.93}, {"name": "blue", "value": 7, "percent": 4.93}, {"name": "3", "value": 6, "percent": 4.23}, {"name": "black", "value": 6, "percent": 4.23}, {"name": "1", "value": 6, "percent": 4.23}, {"name": "sitting", "value": 5, "percent": 3.52}, {"name": "green", "value": 4, "percent": 2.82}, {"name": "no", "value": 4, "percent": 2.82}, {"name": "white", "value": 4, "percent": 2.82}, {"name": "brown", "value": 4, "percent": 2.82}, {"name": "pink", "value": 3, "percent": 2.11}, {"name": "background", "value": 3, "percent": 2.11}, {"name": "window", "value": 3, "percent": 2.11}, {"name": "wall", "value": 3, "percent": 2.11}, {"name": "toy", "value": 3, "percent": 2.11}, {"name": "microphone", "value": 3, "percent": 2.11}, {"name": "knife", "value": 3, "percent": 2.11}, {"name": "clock", "value": 2, "percent": 1.41}, {"name": "bottle", "value": 2, "percent": 1.41}, {"name": "stick", "value": 2, "percent": 1.41}, {"name": "tree", "value": 2, "percent": 1.41}, {"name": "tv", "value": 2, "percent": 1.41}, {"name": "bird", "value": 2, "percent": 1.41}, {"name": "plate", "value": 2, "percent": 1.41}, {"name": "left", "value": 2, "percent": 1.41}, {"name": "floor", "value": 2, "percent": 1.41}], "len_ques": [{"name": 0, "value": 0, "percent": 0.0}, {"name": 1, "value": 0, "percent": 0.0}, {"name": 3, "value": 1, "percent": 0.55}, {"name": 4, "value": 10, "percent": 5.46}, {"name": 5, "value": 65, "percent": 35.52}, {"name": 6, "value": 35, "percent": 19.13}, {"name": 7, "value": 29, "percent": 15.85}, {"name": 8, "value": 21, "percent": 11.48}, {"name": 9, "value": 12, "percent": 6.56}, {"name": 10, "value": 5, "percent": 2.73}, {"name": 11, "value": 2, "percent": 1.09}, {"name": 12, "value": 1, "percent": 0.55}, {"name": 13, "value": 1, "percent": 0.55}, {"name": 14, "value": 1, "percent": 0.55}], "nest_question": [{"name": "", "value": 183, "children": [{"name": "", "value": 183, "fill": "transparent", "children": [{"name": "", "value": 183, "fill": "transparent", "children": [{"name": "", "value": 183, "fill": "transparent", "children": [{"name": "", "value": 183, "fill": "transparent"}]}]}]}], "fill": "transparent"}], "first_word": [{"name": "what", "value": 116, "percent": 63.39}, {"name": "is", "value": 27, "percent": 14.75}, {"name": "how", "value": 24, "percent": 13.11}, {"name": "are", "value": 10, "percent": 5.46}, {"name": "where", "value": 6, "percent": 3.28}], "qa_stack": {"data": [{"name": "are", "yes": 60, "no": 20, "both": 10, "inside": 10, "1": 0, "green": 0, "clock": 0, "stick": 0, "other": 0, "floor": 0, "plate": 0, "tv": 0, "window": 0, "white": 0, "black": 0, "background": 0, "wall": 0, "left": 0, "pink": 0, "3": 0, "2": 0, "sitting": 0, "purple": 0, "knife": 0, "bottle": 0, "middle": 0, "brown": 0, "tree": 0, "standing": 0, "bird": 0, "red": 0, "few": 0, "house": 0, "4": 0, "microphone": 0, "blue": 0, "toy": 0}, {"name": "how", "2": 38, "1": 25, "3": 25, "4": 8, "few": 4, "green": 0, "clock": 0, "stick": 0, "other": 0, "floor": 0, "plate": 0, "tv": 0, "window": 0, "white": 0, "inside": 0, "black": 0, "background": 0, "wall": 0, "left": 0, "pink": 0, "sitting": 0, "purple": 0, "knife": 0, "bottle": 0, "middle": 0, "brown": 0, "both": 0, "tree": 0, "standing": 0, "bird": 0, "red": 0, "house": 0, "no": 0, "microphone": 0, "blue": 0, "toy": 0, "yes": 0}, {"name": "is", "yes": 74, "sitting": 11, "no": 7, "house": 4, "standing": 4, "1": 0, "green": 0, "clock": 0, "stick": 0, "other": 0, "floor": 0, "plate": 0, "tv": 0, "window": 0, "white": 0, "inside": 0, "black": 0, "background": 0, "wall": 0, "left": 0, "pink": 0, "3": 0, "2": 0, "purple": 0, "knife": 0, "bottle": 0, "middle": 0, "brown": 0, "both": 0, "tree": 0, "bird": 0, "red": 0, "few": 0, "4": 0, "microphone": 0, "blue": 0, "toy": 0}, {"name": "what", "red": 7, "purple": 6, "blue": 6, "standing": 5, "black": 5, "brown": 3, "green": 3, "white": 3, "wall": 3, "microphone": 3, "toy": 3, "pink": 3, "knife": 3, "window": 3, "sitting": 2, "stick": 2, "clock": 2, "bird": 2, "tree": 2, "plate": 2, "bottle": 2, "tv": 2, "other": 28, "1": 0, "floor": 0, "inside": 0, "background": 0, "left": 0, "3": 0, "2": 0, "middle": 0, "both": 0, "few": 0, "house": 0, "4": 0, "no": 0, "yes": 0}, {"name": "where", "background": 50, "floor": 17, "left": 17, "middle": 16, "1": 0, "green": 0, "clock": 0, "stick": 0, "other": 0, "plate": 0, "tv": 0, "window": 0, "white": 0, "inside": 0, "black": 0, "wall": 0, "pink": 0, "3": 0, "2": 0, "sitting": 0, "purple": 0, "knife": 0, "bottle": 0, "brown": 0, "both": 0, "tree": 0, "standing": 0, "bird": 0, "red": 0, "few": 0, "house": 0, "4": 0, "no": 0, "microphone": 0, "blue": 0, "toy": 0, "yes": 0}], "keys": ["yes", "no", "both", "inside", "1", "green", "clock", "stick", "other", "floor", "plate", "tv", "window", "white", "black", "background", "wall", "left", "pink", "3", "2", "sitting", "purple", "knife", "bottle", "middle", "brown", "tree", "standing", "bird", "red", "few", "house", "4", "microphone", "blue", "toy"]}, "qt_stack": {"data": [{"name": "are", "object recognition": 50, "spatial": 20, "action recognition": 10, "attribute classification": 10, "comparative": 10, "counting": 0, "other": 0}, {"name": "how", "counting": 100, "spatial": 0, "comparative": 0, "object recognition": 0, "other": 0, "attribute classification": 0, "action recognition": 0}, {"name": "is", "object recognition": 70, "action recognition": 15, "attribute classification": 7, "spatial": 4, "comparative": 4, "counting": 0, "other": 0}, {"name": "what", "attribute classification": 43, "object recognition": 42, "action recognition": 9, "spatial": 5, "other": 1, "comparative": 0, "counting": 0}, {"name": "where", "spatial": 100, "comparative": 0, "counting": 0, "object recognition": 0, "other": 0, "attribute classification": 0, "action recognition": 0}], "keys": ["object recognition", "spatial", "action recognition", "attribute classification", "comparative", "counting", "other"]}, "ques_len_list": [6, 7, 8, 5, 6, 6, 4, 7, 7, 5, 5, 5, 5, 5, 5, 5, 5, 7, 3, 7, 5, 8, 5, 7, 7, 8, 7, 5, 5, 5, 8, 6, 5, 5, 6, 6, 6, 6, 7, 6, 6, 5, 9, 6, 6, 9, 9, 7, 11, 7, 4, 4, 7, 7, 7, 9, 7, 7, 6, 8, 7, 5, 6, 5, 5, 5, 5, 4, 4, 9, 5, 6, 5, 14, 5, 5, 5, 5, 10, 8, 5, 5, 6, 6, 6, 6, 6, 6, 6, 5, 5, 6, 6, 9, 5, 5, 7, 5, 5, 9, 6, 6, 6, 6, 10, 7, 5, 7, 4, 7, 4, 7, 7, 5, 5, 5, 5, 6, 5, 6, 5, 9, 9, 5, 5, 8, 8, 5, 5, 5, 5, 7, 4, 7, 5, 5, 8, 7, 12, 8, 10, 7, 10, 5, 6, 8, 8, 8, 5, 5, 5, 8, 8, 6, 6, 6, 8, 5, 5, 8, 8, 8, 5, 5, 5, 5, 13, 7, 9, 4, 5, 9, 8, 9, 10, 6, 11, 5, 7, 5, 8, 4, 5], "answer_type": [{"name": "other", "value": 130, "percent": 71.04, "fill": "#F06292"}, {"name": "yes/no", "value": 30, "percent": 16.39, "fill": "#4FC3F7"}, {"name": "number", "value": 23, "percent": 12.57, "fill": "#AED581"}], "question_bag": [{"text": "the", "value": 191}, {"text": "is", "value": 136}, {"text": "what", "value": 116}, {"text": "color", "value": 45}, {"text": "are", "value": 44}, {"text": "in", "value": 42}, {"text": "there", "value": 34}, {"text": "on", "value": 30}, {"text": "holding", "value": 28}, {"text": "man", "value": 26}, {"text": "of", "value": 26}, {"text": "how", "value": 24}, {"text": "many", "value": 24}, {"text": "person", "value": 21}, {"text": "people", "value": 20}, {"text": "sitting", "value": 12}, {"text": "image", "value": 10}, {"text": "wall", "value": 10}, {"text": "woman", "value": 10}, {"text": "front", "value": 9}, {"text": "standing", "value": 9}, {"text": "background", "value": 8}, {"text": "behind", "value": 8}, {"text": "doing", "value": 8}, {"text": "hair", "value": 7}, {"text": "hand", "value": 7}, {"text": "or", "value": 7}, {"text": "table", "value": 7}, {"text": "building", "value": 6}, {"text": "chair", "value": 6}, {"text": "his", "value": 6}, {"text": "wearing", "value": 6}, {"text": "where", "value": 6}, {"text": "left", "value": 5}, {"text": "they", "value": 4}, {"text": "any", "value": 3}, {"text": "bench", "value": 3}, {"text": "character", "value": 3}, {"text": "glasses", "value": 3}, {"text": "her", "value": 3}, {"text": "other", "value": 3}, {"text": "room", "value": 3}, {"text": "shirt", "value": 3}, {"text": "side", "value": 3}, {"text": "walls", "value": 3}, {"text": "and", "value": 2}, {"text": "at", "value": 2}, {"text": "be", "value": 2}, {"text": "books", "value": 2}, {"text": "boys", "value": 2}, {"text": "camera", "value": 2}, {"text": "car", "value": 2}, {"text": "chairs", "value": 2}, {"text": "clock", "value": 2}, {"text": "collar", "value": 2}, {"text": "couch", "value": 2}, {"text": "curtain", "value": 2}, {"text": "dog", "value": 2}, {"text": "door", "value": 2}, {"text": "dress", "value": 2}, {"text": "glass", "value": 2}, {"text": "ground", "value": 2}, {"text": "hat", "value": 2}, {"text": "he", "value": 2}, {"text": "jumpsuit", "value": 2}, {"text": "made", "value": 2}, {"text": "men", "value": 2}, {"text": "mouth", "value": 2}, {"text": "necklace", "value": 2}, {"text": "right", "value": 2}, {"text": "sign", "value": 2}, {"text": "their", "value": 2}, {"text": "them", "value": 2}, {"text": "tie", "value": 2}, {"text": "tree", "value": 2}, {"text": "window", "value": 2}, {"text": "windows", "value": 2}, {"text": "above", "value": 1}, {"text": "air", "value": 1}, {"text": "airplane", "value": 1}, {"text": "alarm", "value": 1}, {"text": "all", "value": 1}, {"text": "alone", "value": 1}, {"text": "an", "value": 1}, {"text": "another", "value": 1}, {"text": "anything", "value": 1}, {"text": "around", "value": 1}, {"text": "bag", "value": 1}, {"text": "beds", "value": 1}, {"text": "besides", "value": 1}, {"text": "bikes", "value": 1}, {"text": "bird", "value": 1}, {"text": "blue", "value": 1}, {"text": "bow", "value": 1}, {"text": "box", "value": 1}, {"text": "boy", "value": 1}, {"text": "bridge", "value": 1}, {"text": "brushing", "value": 1}, {"text": "buildings", "value": 1}, {"text": "can", "value": 1}], "answer_bag": [{"text": "yes", "value": 26}, {"text": "red", "value": 8}, {"text": "blue", "value": 7}, {"text": "purple", "value": 7}, {"text": "standing", "value": 7}, {"text": "black", "value": 6}, {"text": "sitting", "value": 5}, {"text": "brown", "value": 4}, {"text": "green", "value": 4}, {"text": "no", "value": 4}, {"text": "white", "value": 4}, {"text": "background", "value": 3}, {"text": "knife", "value": 3}, {"text": "microphone", "value": 3}, {"text": "pink", "value": 3}, {"text": "toy", "value": 3}, {"text": "wall", "value": 3}, {"text": "window", "value": 3}, {"text": "bird", "value": 2}, {"text": "bottle", "value": 2}, {"text": "clock", "value": 2}, {"text": "floor", "value": 2}, {"text": "left", "value": 2}, {"text": "plate", "value": 2}, {"text": "stick", "value": 2}, {"text": "tree", "value": 2}, {"text": "tv", "value": 2}, {"text": "ball", "value": 1}, {"text": "bat", "value": 1}, {"text": "blonde", "value": 1}, {"text": "book", "value": 1}, {"text": "both", "value": 1}, {"text": "box", "value": 1}, {"text": "building", "value": 1}, {"text": "cake", "value": 1}, {"text": "chair", "value": 1}, {"text": "counter", "value": 1}, {"text": "door", "value": 1}, {"text": "eyeglasses", "value": 1}, {"text": "few", "value": 1}, {"text": "fork", "value": 1}, {"text": "glasses", "value": 1}, {"text": "house", "value": 1}, {"text": "inside", "value": 1}, {"text": "laptop", "value": 1}, {"text": "light", "value": 1}, {"text": "middle", "value": 1}, {"text": "mirror", "value": 1}, {"text": "object", "value": 1}, {"text": "orange", "value": 1}, {"text": "painting", "value": 1}, {"text": "paper", "value": 1}, {"text": "people", "value": 1}, {"text": "phone", "value": 1}, {"text": "picture", "value": 1}, {"text": "pillow", "value": 1}, {"text": "plant", "value": 1}, {"text": "refrigerator", "value": 1}, {"text": "remote", "value": 1}, {"text": "sign", "value": 1}, {"text": "sky", "value": 1}, {"text": "sunny", "value": 1}, {"text": "television", "value": 1}, {"text": "toothbrush", "value": 1}, {"text": "umbrella", "value": 1}, {"text": "wood", "value": 1}], "question_answer_bag": [{"text": "the", "value": 191}, {"text": "is", "value": 136}, {"text": "what", "value": 116}, {"text": "color", "value": 45}, {"text": "are", "value": 44}, {"text": "in", "value": 42}, {"text": "there", "value": 34}, {"text": "on", "value": 30}, {"text": "holding", "value": 28}, {"text": "man", "value": 26}, {"text": "of", "value": 26}, {"text": "yes", "value": 26}, {"text": "how", "value": 24}, {"text": "many", "value": 24}, {"text": "people", "value": 21}, {"text": "person", "value": 21}, {"text": "sitting", "value": 17}, {"text": "standing", "value": 16}, {"text": "wall", "value": 13}, {"text": "background", "value": 11}, {"text": "image", "value": 10}, {"text": "woman", "value": 10}, {"text": "front", "value": 9}, {"text": "behind", "value": 8}, {"text": "blue", "value": 8}, {"text": "doing", "value": 8}, {"text": "red", "value": 8}, {"text": "building", "value": 7}, {"text": "chair", "value": 7}, {"text": "hair", "value": 7}, {"text": "hand", "value": 7}, {"text": "left", "value": 7}, {"text": "or", "value": 7}, {"text": "purple", "value": 7}, {"text": "table", "value": 7}, {"text": "black", "value": 6}, {"text": "his", "value": 6}, {"text": "wearing", "value": 6}, {"text": "where", "value": 6}, {"text": "window", "value": 5}, {"text": "brown", "value": 4}, {"text": "clock", "value": 4}, {"text": "glasses", "value": 4}, {"text": "green", "value": 4}, {"text": "no", "value": 4}, {"text": "they", "value": 4}, {"text": "toy", "value": 4}, {"text": "tree", "value": 4}, {"text": "white", "value": 4}, {"text": "any", "value": 3}, {"text": "bench", "value": 3}, {"text": "bird", "value": 3}, {"text": "character", "value": 3}, {"text": "door", "value": 3}, {"text": "her", "value": 3}, {"text": "knife", "value": 3}, {"text": "microphone", "value": 3}, {"text": "other", "value": 3}, {"text": "pink", "value": 3}, {"text": "room", "value": 3}, {"text": "shirt", "value": 3}, {"text": "side", "value": 3}, {"text": "sign", "value": 3}, {"text": "stick", "value": 3}, {"text": "tv", "value": 3}, {"text": "walls", "value": 3}, {"text": "and", "value": 2}, {"text": "at", "value": 2}, {"text": "be", "value": 2}, {"text": "books", "value": 2}, {"text": "bottle", "value": 2}, {"text": "box", "value": 2}, {"text": "boys", "value": 2}, {"text": "camera", "value": 2}, {"text": "car", "value": 2}, {"text": "chairs", "value": 2}, {"text": "collar", "value": 2}, {"text": "couch", "value": 2}, {"text": "counter", "value": 2}, {"text": "curtain", "value": 2}, {"text": "dog", "value": 2}, {"text": "dress", "value": 2}, {"text": "floor", "value": 2}, {"text": "glass", "value": 2}, {"text": "ground", "value": 2}, {"text": "hat", "value": 2}, {"text": "he", "value": 2}, {"text": "house", "value": 2}, {"text": "inside", "value": 2}, {"text": "jumpsuit", "value": 2}, {"text": "made", "value": 2}, {"text": "men", "value": 2}, {"text": "middle", "value": 2}, {"text": "mirror", "value": 2}, {"text": "mouth", "value": 2}, {"text": "necklace", "value": 2}, {"text": "object", "value": 2}, {"text": "phone", "value": 2}, {"text": "picture", "value": 2}, {"text": "plate", "value": 2}], "category_worker": [{"0 worker": 103, "1 worker": 80, "name": "incorrect"}, {"2 workers": 183, "name": "partially incorrect"}, {"0 worker": 157, "1 worker": 26, "name": "ambiguous"}, {"0 worker": 162, "1 worker": 21, "name": "partially correct"}, {"0 worker": 127, "1 worker": 56, "name": "correct"}]}