{"categories": [{"name": "incorrect", "value": 706, "percent": 11.0, "fill": "#E74C3C"}, {"name": "partially incorrect", "value": 90, "percent": 1.0, "fill": "#F39C12"}, {"name": "ambiguous", "value": 4298, "percent": 69.0, "fill": "#512E5F"}, {"name": "partially correct", "value": 325, "percent": 5.0, "fill": "#82E0AA"}, {"name": "correct", "value": 842, "percent": 13.0, "fill": "#28B463"}], "cumulative_category": [{"name": "3 Workers", "correct & partially correct": 0, "correct": 0, "partially correct": 0, "ambiguous": 124, "partially incorrect": 0, "incorrect": 0, "incorrect & partially incorrect": 0}, {"name": "2 Workers", "correct & partially correct": 0, "correct": 0, "partially correct": 0, "ambiguous": 2087, "partially incorrect": 0, "incorrect": 0, "incorrect & partially incorrect": 0}, {"name": "1 Worker", "correct & partially correct": 1167, "correct": 842, "partially correct": 325, "ambiguous": 2087, "partially incorrect": 90, "incorrect": 706, "incorrect & partially incorrect": 796}, {"name": "Total", "correct & partially correct": 2087, "correct": 2087, "partially correct": 2087, "ambiguous": 2087, "partially incorrect": 2087, "incorrect": 2087, "incorrect & partially incorrect": 2087}], "topics": [{"name": "attribute classification", "value": 838, "percent": 40.15, "fill": "#F06292"}, {"name": "object recognition", "value": 740, "percent": 35.46, "fill": "#4FC3F7"}, {"name": "action recognition", "value": 195, "percent": 9.34, "fill": "#AED581"}, {"name": "spatial", "value": 168, "percent": 8.05, "fill": "#FF8A65"}, {"name": "counting", "value": 96, "percent": 4.6, "fill": "#BA68C8"}, {"name": "reasoning", "value": 28, "percent": 1.34, "fill": "#4DB6AC"}, {"name": "comparative", "value": 22, "percent": 1.05, "fill": "#FFF176"}], "answer_list": [{"name": "yes", "value": 304, "percent": 19.88}, {"name": "blue", "value": 162, "percent": 10.6}, {"name": "standing", "value": 93, "percent": 6.08}, {"name": "red", "value": 88, "percent": 5.76}, {"name": "white", "value": 87, "percent": 5.69}, {"name": "green", "value": 82, "percent": 5.36}, {"name": "purple", "value": 81, "percent": 5.3}, {"name": "black", "value": 80, "percent": 5.23}, {"name": "sitting", "value": 75, "percent": 4.91}, {"name": "2", "value": 48, "percent": 3.14}, {"name": "brown", "value": 44, "percent": 2.88}, {"name": "pink", "value": 43, "percent": 2.81}, {"name": "no", "value": 30, "percent": 1.96}, {"name": "wall", "value": 30, "percent": 1.96}, {"name": "phone", "value": 26, "percent": 1.7}, {"name": "wood", "value": 25, "percent": 1.64}, {"name": "window", "value": 23, "percent": 1.5}, {"name": "building", "value": 20, "percent": 1.31}, {"name": "book", "value": 19, "percent": 1.24}, {"name": "gray", "value": 19, "percent": 1.24}, {"name": "1", "value": 19, "percent": 1.24}, {"name": "3", "value": 17, "percent": 1.11}, {"name": "tree", "value": 16, "percent": 1.05}, {"name": "left", "value": 16, "percent": 1.05}, {"name": "floor", "value": 14, "percent": 0.92}, {"name": "sign", "value": 14, "percent": 0.92}, {"name": "object", "value": 14, "percent": 0.92}, {"name": "chair", "value": 14, "percent": 0.92}, {"name": "background", "value": 13, "percent": 0.85}, {"name": "laptop", "value": 13, "percent": 0.85}], "len_ques": [{"name": 0, "value": 0, "percent": 0.0}, {"name": 1, "value": 0, "percent": 0.0}, {"name": 3, "value": 6, "percent": 0.29}, {"name": 4, "value": 76, "percent": 3.64}, {"name": 5, "value": 654, "percent": 31.34}, {"name": 6, "value": 556, "percent": 26.64}, {"name": 7, "value": 289, "percent": 13.85}, {"name": 8, "value": 303, "percent": 14.52}, {"name": 9, "value": 102, "percent": 4.89}, {"name": 10, "value": 57, "percent": 2.73}, {"name": 11, "value": 26, "percent": 1.25}, {"name": 12, "value": 12, "percent": 0.57}, {"name": 13, "value": 2, "percent": 0.1}, {"name": 14, "value": 2, "percent": 0.1}, {"name": 15, "value": 1, "percent": 0.05}, {"name": 18, "value": 1, "percent": 0.05}], "nest_question": [{"name": "what", "value": 1478, "children": [{"name": "color", "value": 580, "children": [{"name": "is", "value": 442, "children": [{"name": "the", "value": 435, "children": [{"name": "", "value": 435, "children": [{"name": "", "value": 435, "fill": "transparent"}], "fill": "transparent"}], "fill": "#F48FB1"}, {"name": "", "value": 7, "children": [{"name": "", "value": 7, "fill": "transparent"}], "fill": "transparent"}], "fill": "#F06292"}, {"name": "", "value": 138, "children": [{"name": "", "value": 138, "fill": "transparent", "children": [{"name": "", "value": 138, "fill": "transparent"}]}], "fill": "transparent"}], "fill": "#EC407A"}, {"name": "is", "value": 784, "children": [{"name": "the", "value": 489, "children": [{"name": "", "value": 489, "children": [{"name": "", "value": 489, "fill": "transparent"}], "fill": "transparent"}], "fill": "#F06292"}, {"name": "", "value": 295, "children": [{"name": "", "value": 295, "fill": "transparent", "children": [{"name": "", "value": 295, "fill": "transparent"}]}], "fill": "transparent"}], "fill": "#EC407A"}, {"name": "", "value": 114, "children": [{"name": "", "value": 114, "fill": "transparent", "children": [{"name": "", "value": 114, "fill": "transparent", "children": [{"name": "", "value": 114, "fill": "transparent"}]}]}], "fill": "transparent"}], "fill": "#E91E63"}, {"name": "", "value": 609, "children": [{"name": "", "value": 609, "fill": "transparent", "children": [{"name": "", "value": 609, "fill": "transparent", "children": [{"name": "", "value": 609, "fill": "transparent", "children": [{"name": "", "value": 609, "fill": "transparent"}]}]}]}], "fill": "transparent"}], "first_word": [{"name": "what", "value": 1478, "percent": 70.82}, {"name": "is", "value": 313, "percent": 15.0}, {"name": "how", "value": 100, "percent": 4.79}, {"name": "are", "value": 93, "percent": 4.46}, {"name": "where", "value": 73, "percent": 3.5}, {"name": "who", "value": 14, "percent": 0.67}, {"name": "can", "value": 9, "percent": 0.43}, {"name": "do", "value": 4, "percent": 0.19}, {"name": "does", "value": 3, "percent": 0.14}], "qa_stack": {"data": [{"name": "are", "yes": 60, "sitting": 13, "no": 12, "standing": 8, "2": 1, "phone": 1, "outside": 1, "ground": 1, "front": 1, "cup": 1, "behind": 1, "1": 0, "green": 0, "building": 0, "long": 0, "room": 0, "bed": 0, "woman": 0, "other": 0, "man": 0, "floor": 0, "group": 0, "wood": 0, "window": 0, "bench": 0, "forest": 0, "person": 0, "right": 0, "white": 0, "black": 0, "left": 0, "wall": 0, "background": 0, "pink": 0, "many": 0, "courtroom": 0, "3": 0, "purple": 0, "open": 0, "kitchen": 0, "middle": 0, "brown": 0, "both": 0, "tree": 0, "girl": 0, "red": 0, "few": 0, "chair": 0, "gray": 0, "sidewalk": 0, "4": 0, "table": 0, "couch": 0, "book": 0, "blue": 0, "balcony": 0}, {"name": "can", "yes": 67, "no": 33, "1": 0, "green": 0, "building": 0, "long": 0, "room": 0, "bed": 0, "woman": 0, "other": 0, "behind": 0, "man": 0, "floor": 0, "group": 0, "outside": 0, "wood": 0, "window": 0, "bench": 0, "forest": 0, "person": 0, "right": 0, "white": 0, "black": 0, "left": 0, "wall": 0, "background": 0, "pink": 0, "many": 0, "courtroom": 0, "3": 0, "2": 0, "sitting": 0, "purple": 0, "open": 0, "kitchen": 0, "middle": 0, "brown": 0, "both": 0, "tree": 0, "phone": 0, "standing": 0, "girl": 0, "red": 0, "few": 0, "chair": 0, "ground": 0, "gray": 0, "sidewalk": 0, "4": 0, "table": 0, "couch": 0, "front": 0, "book": 0, "blue": 0, "balcony": 0, "cup": 0}, {"name": "do", "yes": 100, "1": 0, "green": 0, "building": 0, "long": 0, "room": 0, "bed": 0, "woman": 0, "other": 0, "behind": 0, "man": 0, "floor": 0, "group": 0, "outside": 0, "wood": 0, "window": 0, "bench": 0, "forest": 0, "person": 0, "right": 0, "white": 0, "black": 0, "left": 0, "wall": 0, "background": 0, "pink": 0, "many": 0, "courtroom": 0, "3": 0, "2": 0, "sitting": 0, "purple": 0, "open": 0, "kitchen": 0, "middle": 0, "brown": 0, "both": 0, "tree": 0, "phone": 0, "standing": 0, "girl": 0, "red": 0, "few": 0, "chair": 0, "ground": 0, "gray": 0, "sidewalk": 0, "4": 0, "table": 0, "couch": 0, "front": 0, "no": 0, "book": 0, "blue": 0, "balcony": 0, "cup": 0}, {"name": "does", "yes": 67, "no": 33, "1": 0, "green": 0, "building": 0, "long": 0, "room": 0, "bed": 0, "woman": 0, "other": 0, "behind": 0, "man": 0, "floor": 0, "group": 0, "outside": 0, "wood": 0, "window": 0, "bench": 0, "forest": 0, "person": 0, "right": 0, "white": 0, "black": 0, "left": 0, "wall": 0, "background": 0, "pink": 0, "many": 0, "courtroom": 0, "3": 0, "2": 0, "sitting": 0, "purple": 0, "open": 0, "kitchen": 0, "middle": 0, "brown": 0, "both": 0, "tree": 0, "phone": 0, "standing": 0, "girl": 0, "red": 0, "few": 0, "chair": 0, "ground": 0, "gray": 0, "sidewalk": 0, "4": 0, "table": 0, "couch": 0, "front": 0, "book": 0, "blue": 0, "balcony": 0, "cup": 0}, {"name": "how", "2": 47, "1": 19, "3": 17, "many": 3, "4": 3, "long": 2, "group": 2, "few": 2, "other": 5, "green": 0, "building": 0, "room": 0, "bed": 0, "woman": 0, "behind": 0, "man": 0, "floor": 0, "outside": 0, "wood": 0, "window": 0, "bench": 0, "forest": 0, "person": 0, "right": 0, "white": 0, "black": 0, "left": 0, "wall": 0, "background": 0, "pink": 0, "courtroom": 0, "sitting": 0, "purple": 0, "open": 0, "kitchen": 0, "middle": 0, "brown": 0, "both": 0, "tree": 0, "phone": 0, "standing": 0, "girl": 0, "red": 0, "chair": 0, "ground": 0, "gray": 0, "sidewalk": 0, "table": 0, "couch": 0, "front": 0, "no": 0, "book": 0, "blue": 0, "balcony": 0, "cup": 0, "yes": 0}, {"name": "is", "yes": 75, "sitting": 6, "no": 5, "standing": 5, "open": 1, "other": 8, "1": 0, "green": 0, "building": 0, "long": 0, "room": 0, "bed": 0, "woman": 0, "behind": 0, "man": 0, "floor": 0, "group": 0, "outside": 0, "wood": 0, "window": 0, "bench": 0, "forest": 0, "person": 0, "right": 0, "white": 0, "black": 0, "left": 0, "wall": 0, "background": 0, "pink": 0, "many": 0, "courtroom": 0, "3": 0, "2": 0, "purple": 0, "kitchen": 0, "middle": 0, "brown": 0, "both": 0, "tree": 0, "phone": 0, "girl": 0, "red": 0, "few": 0, "chair": 0, "ground": 0, "gray": 0, "sidewalk": 0, "4": 0, "table": 0, "couch": 0, "front": 0, "book": 0, "blue": 0, "balcony": 0, "cup": 0}, {"name": "what", "blue": 11, "red": 6, "white": 6, "purple": 5, "green": 5, "black": 5, "standing": 5, "brown": 3, "sitting": 3, "pink": 3, "wall": 2, "wood": 2, "phone": 2, "window": 1, "gray": 1, "building": 1, "book": 1, "tree": 1, "other": 37, "1": 0, "long": 0, "room": 0, "bed": 0, "woman": 0, "behind": 0, "man": 0, "floor": 0, "group": 0, "outside": 0, "bench": 0, "forest": 0, "person": 0, "right": 0, "left": 0, "background": 0, "many": 0, "courtroom": 0, "3": 0, "2": 0, "open": 0, "kitchen": 0, "middle": 0, "both": 0, "girl": 0, "few": 0, "chair": 0, "ground": 0, "sidewalk": 0, "4": 0, "table": 0, "couch": 0, "front": 0, "no": 0, "balcony": 0, "cup": 0, "yes": 0}, {"name": "where", "left": 16, "background": 12, "floor": 12, "ground": 10, "right": 10, "table": 7, "couch": 4, "sidewalk": 4, "room": 3, "wall": 3, "chair": 3, "courtroom": 3, "building": 1, "outside": 1, "standing": 1, "kitchen": 1, "forest": 1, "balcony": 1, "bed": 1, "middle": 1, "bench": 1, "long": 1, "other": 3, "1": 0, "green": 0, "woman": 0, "behind": 0, "man": 0, "group": 0, "wood": 0, "window": 0, "person": 0, "white": 0, "black": 0, "pink": 0, "many": 0, "3": 0, "2": 0, "sitting": 0, "purple": 0, "open": 0, "brown": 0, "both": 0, "tree": 0, "phone": 0, "girl": 0, "red": 0, "few": 0, "gray": 0, "4": 0, "front": 0, "no": 0, "book": 0, "blue": 0, "cup": 0, "yes": 0}, {"name": "who", "woman": 36, "man": 36, "person": 14, "girl": 7, "both": 7, "1": 0, "green": 0, "building": 0, "long": 0, "room": 0, "bed": 0, "other": 0, "behind": 0, "floor": 0, "group": 0, "outside": 0, "wood": 0, "window": 0, "bench": 0, "forest": 0, "right": 0, "white": 0, "black": 0, "left": 0, "wall": 0, "background": 0, "pink": 0, "many": 0, "courtroom": 0, "3": 0, "2": 0, "sitting": 0, "purple": 0, "open": 0, "kitchen": 0, "middle": 0, "brown": 0, "tree": 0, "phone": 0, "standing": 0, "red": 0, "few": 0, "chair": 0, "ground": 0, "gray": 0, "sidewalk": 0, "4": 0, "table": 0, "couch": 0, "front": 0, "no": 0, "book": 0, "blue": 0, "balcony": 0, "cup": 0, "yes": 0}], "keys": ["yes", "sitting", "no", "standing", "2", "phone", "outside", "ground", "front", "cup", "behind", "1", "green", "building", "long", "room", "bed", "woman", "other", "man", "floor", "group", "wood", "window", "bench", "forest", "person", "right", "white", "black", "left", "wall", "background", "pink", "many", "courtroom", "3", "purple", "open", "kitchen", "middle", "brown", "both", "tree", "girl", "red", "few", "chair", "gray", "sidewalk", "4", "table", "couch", "book", "blue", "balcony"]}, "qt_stack": {"data": [{"name": "are", "object recognition": 42, "action recognition": 23, "spatial": 12, "comparative": 11, "attribute classification": 6, "reasoning": 5, "counting": 1, "other": 0}, {"name": "can", "object recognition": 67, "reasoning": 22, "spatial": 11, "comparative": 0, "counting": 0, "other": 0, "attribute classification": 0, "action recognition": 0}, {"name": "do", "object recognition": 50, "reasoning": 25, "comparative": 25, "spatial": 0, "counting": 0, "other": 0, "attribute classification": 0, "action recognition": 0}, {"name": "does", "reasoning": 33, "object recognition": 33, "attribute classification": 33, "other": 1, "spatial": 0, "comparative": 0, "counting": 0, "action recognition": 0}, {"name": "how", "counting": 93, "attribute classification": 2, "action recognition": 2, "other": 3, "spatial": 0, "comparative": 0, "object recognition": 0, "reasoning": 0}, {"name": "is", "object recognition": 69, "action recognition": 13, "attribute classification": 7, "spatial": 4, "comparative": 3, "reasoning": 3, "other": 1, "counting": 0}, {"name": "what", "attribute classification": 54, "object recognition": 32, "action recognition": 9, "spatial": 5, "comparative": 0, "counting": 0, "other": 0, "reasoning": 0}, {"name": "where", "spatial": 100, "comparative": 0, "counting": 0, "object recognition": 0, "other": 0, "reasoning": 0, "attribute classification": 0, "action recognition": 0}, {"name": "who", "object recognition": 50, "attribute classification": 36, "action recognition": 14, "spatial": 0, "comparative": 0, "counting": 0, "other": 0, "reasoning": 0}], "keys": ["object recognition", "action recognition", "spatial", "comparative", "attribute classification", "reasoning", "counting", "other"]}, "ques_len_list": [5, 5, 7, 9, 4, 6, 6, 5, 6, 5, 5, 5, 9, 10, 6, 6, 6, 6, 6, 6, 6, 6, 6, 6, 6, 9, 5, 5, 5, 7, 6, 4, 10, 4, 7, 7, 7, 7, 7, 7, 7, 4, 7, 8, 7, 8, 7, 4, 6, 6, 6, 6, 9, 7, 8, 7, 6, 6, 8, 6, 3, 8, 6, 7, 6, 3, 6, 6, 4, 5, 4, 5, 5, 5, 5, 5, 5, 8, 8, 8, 6, 6, 6, 6, 8, 8, 6, 6, 5, 5, 7, 5, 5, 5, 5, 7, 7, 8, 11, 5, 5, 5, 6, 5, 5, 5, 8, 7, 8, 7, 5, 5, 5, 6, 8, 3, 7, 5, 6, 5, 7, 8, 5, 5, 7, 7, 8, 7, 7, 7, 7, 7, 7, 7, 8, 8, 8, 8, 8, 5, 5, 5, 5, 5, 5, 5, 8, 7, 8, 6, 10, 5, 8, 5, 7, 5, 5, 5, 5, 6, 7, 5, 10, 5, 5, 7, 7, 7, 7, 5, 6, 5, 6, 6, 3, 5, 5, 5, 5, 5, 3, 8, 6, 5, 6, 6, 6, 6, 11, 6, 6, 4, 5, 10, 6, 6, 5, 4, 12, 6, 6, 7, 7, 7, 6, 8, 6, 4, 9, 7, 6, 6, 5, 9, 7, 10, 6, 6, 6, 6, 6, 6, 6, 6, 6, 9, 9, 7, 6, 6, 6, 6, 6, 6, 6, 6, 7, 6, 6, 6, 6, 6, 5, 5, 5, 6, 10, 8, 5, 6, 5, 7, 6, 6, 6, 9, 8, 6, 6, 6, 6, 6, 6, 6, 6, 6, 6, 6, 5, 6, 4, 9, 7, 7, 6, 9, 7, 6, 6, 7, 6, 6, 10, 6, 6, 5, 6, 6, 6, 6, 4, 6, 6, 7, 5, 7, 7, 5, 7, 8, 7, 9, 7, 7, 7, 7, 4, 7, 8, 4, 4, 8, 8, 7, 7, 7, 7, 7, 7, 4, 7, 7, 7, 7, 7, 7, 8, 7, 8, 4, 4, 9, 7, 7, 7, 7, 7, 7, 5, 5, 7, 4, 8, 8, 4, 7, 8, 7, 7, 10, 7, 4, 4, 7, 7, 7, 7, 7, 7, 7, 7, 7, 5, 10, 7, 7, 7, 10, 7, 7, 8, 8, 8, 8, 7, 7, 4, 4, 7, 8, 5, 10, 7, 4, 7, 7, 7, 7, 7, 4, 4, 7, 5, 7, 7, 9, 7, 7, 7, 4, 4, 4, 4, 8, 7, 5, 5, 7, 8, 7, 7, 7, 7, 7, 7, 7, 9, 8, 7, 6, 7, 7, 4, 4, 4, 7, 8, 8, 8, 5, 7, 11, 7, 7, 8, 7, 8, 8, 6, 6, 6, 6, 6, 6, 8, 6, 6, 6, 7, 6, 7, 7, 6, 6, 6, 6, 7, 6, 5, 5, 5, 5, 5, 5, 8, 5, 5, 5, 5, 5, 5, 5, 5, 5, 5, 8, 5, 5, 8, 6, 6, 6, 6, 5, 4, 5, 8, 6, 6, 8, 5, 4, 4, 7, 4, 4, 4, 4, 4, 4, 7, 4, 7, 6, 5, 6, 5, 5, 5, 8, 6, 5, 5, 5, 5, 5, 6, 6, 9, 5, 8, 5, 10, 6, 6, 12, 5, 5, 6, 8, 7, 6, 6, 6, 6, 6, 6, 6, 6, 6, 6, 6, 6, 6, 6, 6, 6, 6, 6, 11, 5, 5, 6, 6, 6, 6, 6, 6, 6, 6, 6, 6, 6, 8, 8, 10, 11, 8, 5, 5, 5, 5, 5, 5, 6, 9, 6, 6, 6, 6, 6, 8, 6, 5, 10, 7, 7, 7, 5, 5, 5, 5, 5, 9, 8, 5, 5, 5, 5, 5, 6, 6, 6, 6, 6, 5, 6, 5, 8, 6, 5, 6, 6, 6, 9, 6, 7, 5, 5, 5, 5, 5, 5, 5, 11, 9, 5, 5, 5, 5, 5, 5, 5, 5, 5, 8, 8, 5, 5, 8, 7, 8, 10, 5, 5, 5, 5, 6, 6, 5, 5, 8, 5, 5, 5, 5, 5, 5, 5, 5, 6, 5, 5, 6, 6, 6, 6, 5, 5, 5, 9, 5, 6, 5, 5, 6, 6, 6, 6, 9, 6, 6, 5, 8, 8, 5, 5, 5, 5, 5, 5, 5, 7, 11, 12, 5, 5, 5, 5, 8, 8, 8, 9, 6, 6, 6, 7, 6, 6, 6, 6, 6, 6, 6, 6, 9, 6, 6, 6, 6, 6, 6, 6, 6, 6, 6, 6, 6, 6, 6, 6, 6, 6, 6, 6, 6, 6, 6, 6, 6, 6, 6, 6, 6, 6, 6, 6, 6, 6, 6, 6, 6, 6, 9, 9, 18, 6, 6, 6, 6, 6, 6, 6, 6, 6, 6, 6, 6, 6, 6, 6, 6, 6, 6, 6, 6, 6, 6, 6, 6, 6, 6, 6, 6, 6, 6, 6, 6, 6, 6, 6, 6, 6, 6, 6, 6, 6, 6, 6, 6, 6, 6, 6, 6, 6, 6, 6, 6, 6, 6, 6, 6, 6, 6, 6, 6, 9, 5, 5, 5, 5, 12, 7, 7, 7, 7, 7, 9, 6, 6, 6, 6, 9, 6, 6, 11, 6, 6, 6, 9, 9, 9, 9, 6, 6, 6, 6, 6, 6, 6, 6, 6, 6, 6, 6, 6, 5, 5, 5, 5, 5, 6, 9, 6, 6, 8, 5, 5, 5, 5, 5, 5, 5, 5, 5, 5, 7, 10, 11, 11, 5, 5, 5, 5, 5, 5, 5, 14, 11, 6, 5, 5, 11, 5, 5, 5, 5, 5, 5, 11, 5, 5, 5, 9, 8, 8, 7, 5, 5, 5, 5, 5, 6, 6, 6, 6, 6, 6, 6, 6, 6, 6, 6, 6, 6, 6, 6, 6, 6, 6, 6, 6, 6, 6, 6, 6, 6, 6, 6, 6, 6, 6, 6, 6, 6, 6, 6, 6, 6, 6, 6, 6, 6, 6, 6, 6, 10, 7, 10, 6, 6, 10, 10, 7, 7, 10, 7, 7, 7, 7, 7, 7, 7, 10, 10, 7, 7, 7, 7, 7, 7, 7, 7, 7, 7, 7, 7, 7, 7, 11, 10, 6, 6, 8, 8, 7, 4, 7, 10, 5, 5, 5, 5, 5, 5, 7, 5, 5, 5, 5, 5, 5, 5, 5, 5, 5, 5, 5, 5, 5, 5, 5, 6, 5, 5, 5, 8, 5, 5, 5, 5, 5, 5, 5, 5, 5, 5, 5, 5, 5, 5, 6, 6, 6, 6, 6, 6, 9, 9, 9, 10, 6, 7, 5, 5, 7, 7, 7, 7, 7, 7, 7, 7, 7, 7, 7, 7, 8, 7, 5, 9, 9, 11, 5, 5, 5, 5, 5, 5, 5, 5, 5, 5, 5, 5, 5, 5, 5, 5, 5, 5, 5, 5, 5, 5, 5, 5, 5, 5, 5, 5, 5, 5, 5, 5, 9, 6, 6, 6, 6, 6, 6, 6, 6, 7, 8, 8, 8, 8, 8, 6, 6, 6, 8, 5, 5, 5, 6, 6, 6, 5, 6, 6, 6, 5, 6, 5, 8, 5, 5, 5, 5, 5, 5, 5, 6, 6, 5, 5, 5, 10, 9, 8, 5, 5, 5, 5, 5, 5, 5, 5, 5, 5, 9, 9, 9, 9, 6, 6, 6, 6, 7, 8, 6, 7, 5, 9, 9, 9, 9, 9, 9, 9, 9, 9, 9, 9, 9, 9, 9, 6, 5, 8, 5, 5, 5, 5, 5, 8, 8, 10, 9, 9, 5, 5, 5, 5, 5, 5, 5, 5, 5, 5, 5, 8, 8, 8, 8, 8, 8, 8, 8, 7, 9, 9, 9, 5, 5, 5, 5, 5, 5, 5, 5, 5, 5, 5, 6, 7, 7, 11, 6, 5, 6, 5, 4, 4, 5, 5, 6, 6, 5, 5, 5, 6, 5, 6, 6, 6, 7, 5, 6, 6, 5, 6, 6, 5, 5, 8, 5, 7, 8, 10, 7, 8, 11, 8, 7, 12, 9, 8, 8, 13, 7, 7, 8, 8, 7, 7, 11, 7, 8, 7, 11, 10, 8, 10, 8, 8, 8, 8, 8, 8, 8, 8, 8, 8, 8, 8, 11, 8, 8, 8, 8, 8, 8, 8, 8, 8, 8, 8, 8, 8, 8, 8, 8, 8, 8, 9, 12, 11, 8, 11, 8, 8, 8, 8, 8, 10, 8, 9, 13, 7, 7, 10, 7, 12, 9, 14, 9, 10, 10, 10, 7, 8, 8, 8, 8, 8, 8, 8, 8, 8, 8, 7, 5, 5, 10, 8, 6, 5, 5, 5, 5, 9, 5, 8, 6, 6, 5, 7, 7, 11, 8, 8, 6, 6, 7, 7, 8, 8, 5, 5, 5, 5, 5, 5, 5, 5, 5, 5, 5, 5, 5, 5, 5, 5, 5, 5, 5, 5, 5, 5, 5, 5, 5, 5, 5, 5, 5, 5, 5, 5, 5, 8, 8, 8, 8, 8, 8, 8, 8, 8, 8, 8, 8, 8, 8, 8, 8, 8, 8, 8, 9, 5, 5, 5, 5, 5, 5, 5, 5, 5, 5, 5, 5, 5, 5, 5, 5, 5, 5, 5, 5, 5, 5, 5, 5, 7, 8, 8, 8, 8, 9, 9, 6, 6, 6, 6, 6, 6, 6, 6, 9, 8, 6, 6, 9, 8, 8, 8, 8, 8, 8, 6, 6, 8, 9, 8, 10, 11, 8, 8, 8, 8, 8, 8, 8, 8, 9, 5, 5, 5, 5, 6, 6, 5, 5, 6, 6, 7, 5, 10, 4, 6, 6, 6, 5, 5, 8, 12, 8, 5, 5, 5, 5, 5, 5, 5, 5, 5, 5, 5, 5, 5, 5, 5, 10, 8, 8, 8, 8, 8, 9, 8, 9, 8, 8, 8, 8, 8, 8, 8, 8, 8, 8, 5, 5, 5, 5, 5, 5, 5, 5, 5, 5, 5, 5, 5, 5, 5, 5, 5, 10, 8, 8, 8, 8, 6, 8, 8, 8, 8, 8, 12, 8, 9, 8, 10, 9, 6, 6, 6, 6, 8, 8, 8, 6, 6, 6, 6, 7, 8, 8, 5, 5, 5, 6, 7, 6, 10, 7, 7, 12, 10, 12, 10, 10, 7, 7, 15, 10, 6, 7, 6, 7, 8, 7, 8, 10, 7, 8, 7, 7, 8, 8, 6, 5, 6, 8, 5, 5, 5, 5, 5, 5, 8, 8, 5, 5, 5, 5, 5, 6, 6, 8, 8, 5, 5, 5, 6, 6, 6, 6, 8, 6, 6, 6, 8, 8, 8, 7, 7, 7, 7, 7, 8, 7, 7, 6, 8, 8, 9, 6, 7, 5, 4, 4, 5, 6, 6, 10, 8, 11, 7, 5, 5, 4, 5, 5, 4, 4, 6, 4, 4, 4, 5, 5, 5, 5, 5, 5, 4, 4, 6, 4, 4, 4, 4, 5, 5, 4, 5, 5, 5, 5, 4, 7, 5, 5, 5, 5, 5, 5, 5, 6, 6, 6, 5, 5, 5, 5, 5, 5, 5, 5, 5, 5, 5, 5, 4, 6, 5, 5, 5, 5, 10, 5, 5, 5, 5, 5, 8, 9, 7, 6, 8, 7, 4, 7, 7, 8, 7, 7, 8, 8, 3, 6, 7, 5, 5, 5, 6, 9, 9, 9, 6, 6, 5, 4, 9, 5, 5, 6, 8, 5, 7, 7, 7, 7, 7, 5, 5, 5, 5, 6, 8, 6, 6, 6, 6, 6, 7, 4, 5, 7, 7, 7, 7, 7, 7, 4, 7, 7, 8, 7, 7, 7, 4, 7, 7, 5, 10, 6, 6, 10, 6, 5, 6, 8, 5, 5, 8, 8, 8, 5, 5, 4, 5, 7, 8, 8, 5, 5, 5, 6, 6, 6, 6, 5, 6, 6, 5, 9, 7, 6, 6, 5, 5, 6, 5, 5, 5, 5, 5, 8, 8, 5, 5, 5, 8, 5, 5, 5, 5, 5, 5, 6, 6, 6, 6, 6, 6, 6, 6, 6, 6, 6, 6, 6, 6, 6, 6, 6, 5, 6, 5, 9, 7, 10, 6, 9, 6, 6, 6, 6, 5, 5, 8, 9, 9, 8, 5, 5, 5, 5, 5, 5, 5, 5, 8, 5, 5, 6, 6, 6, 6, 6, 6, 6, 5, 7, 7, 8, 7, 6, 5, 5, 5, 8, 5, 5, 5, 5, 5, 5, 6, 4, 4, 7, 7, 7, 7, 7, 7, 5, 5, 5, 5, 5, 5, 5, 5, 5, 6, 6, 6, 5, 5, 5, 5, 5, 9, 9, 9, 9, 9, 5, 5, 8, 8, 5, 7, 6, 8, 5, 8, 7, 7, 8, 8, 8, 12, 8, 8, 8, 8, 8, 8, 8, 7, 7, 7, 8, 10, 5, 5, 5, 5, 5, 5, 5, 8, 5, 11, 6, 9, 6, 6, 6, 9, 6, 5, 5, 5, 5, 8, 8, 8, 5, 5, 5, 9, 8, 9, 5, 7, 5, 5, 6, 5, 8, 6, 10, 8, 6, 7, 6, 4, 5, 8, 5, 5, 5, 4, 4, 5, 5, 5, 5, 7, 5, 5, 5, 5, 10, 6], "answer_type": [{"name": "other", "value": 1665, "percent": 79.78, "fill": "#F06292"}, {"name": "yes/no", "value": 334, "percent": 16.0, "fill": "#4FC3F7"}, {"name": "number", "value": 88, "percent": 4.22, "fill": "#AED581"}], "question_bag": [{"text": "the", "value": 2344}, {"text": "is", "value": 1695}, {"text": "what", "value": 1478}, {"text": "color", "value": 716}, {"text": "man", "value": 497}, {"text": "in", "value": 366}, {"text": "are", "value": 362}, {"text": "on", "value": 355}, {"text": "of", "value": 337}, {"text": "there", "value": 255}, {"text": "person", "value": 249}, {"text": "holding", "value": 181}, {"text": "woman", "value": 149}, {"text": "shirt", "value": 148}, {"text": "wearing", "value": 133}, {"text": "people", "value": 127}, {"text": "doing", "value": 122}, {"text": "standing", "value": 117}, {"text": "how", "value": 100}, {"text": "many", "value": 94}, {"text": "sitting", "value": 90}, {"text": "image", "value": 89}, {"text": "behind", "value": 84}, {"text": "or", "value": 84}, {"text": "wall", "value": 77}, {"text": "background", "value": 73}, {"text": "hand", "value": 73}, {"text": "pants", "value": 73}, {"text": "where", "value": 73}, {"text": "hair", "value": 63}, {"text": "front", "value": 54}, {"text": "his", "value": 51}, {"text": "table", "value": 47}, {"text": "left", "value": 44}, {"text": "room", "value": 42}, {"text": "side", "value": 40}, {"text": "right", "value": 38}, {"text": "building", "value": 36}, {"text": "door", "value": 35}, {"text": "made", "value": 35}, {"text": "dress", "value": 33}, {"text": "they", "value": 33}, {"text": "picture", "value": 31}, {"text": "jacket", "value": 29}, {"text": "other", "value": 29}, {"text": "to", "value": 27}, {"text": "at", "value": 25}, {"text": "floor", "value": 25}, {"text": "girl", "value": 25}, {"text": "middle", "value": 25}, {"text": "any", "value": 24}, {"text": "car", "value": 24}, {"text": "suit", "value": 24}, {"text": "their", "value": 23}, {"text": "tie", "value": 23}, {"text": "looking", "value": 20}, {"text": "next", "value": 20}, {"text": "can", "value": 19}, {"text": "ceiling", "value": 19}, {"text": "boy", "value": 18}, {"text": "chair", "value": 18}, {"text": "hat", "value": 18}, {"text": "you", "value": 18}, {"text": "dog", "value": 17}, {"text": "who", "value": 17}, {"text": "window", "value": 17}, {"text": "chairs", "value": 16}, {"text": "see", "value": 16}, {"text": "ground", "value": 15}, {"text": "mirror", "value": 15}, {"text": "sign", "value": 15}, {"text": "bird", "value": 14}, {"text": "couch", "value": 14}, {"text": "does", "value": 14}, {"text": "hanging", "value": 14}, {"text": "have", "value": 14}, {"text": "men", "value": 14}, {"text": "phone", "value": 14}, {"text": "windows", "value": 14}, {"text": "house", "value": 13}, {"text": "objects", "value": 13}, {"text": "top", "value": 13}, {"text": "bed", "value": 12}, {"text": "cap", "value": 12}, {"text": "object", "value": 12}, {"text": "position", "value": 12}, {"text": "sky", "value": 12}, {"text": "children", "value": 11}, {"text": "he", "value": 11}, {"text": "her", "value": 11}, {"text": "located", "value": 11}, {"text": "shoes", "value": 11}, {"text": "and", "value": 10}, {"text": "child", "value": 10}, {"text": "material", "value": 10}, {"text": "tree", "value": 10}, {"text": "an", "value": 9}, {"text": "anything", "value": 9}, {"text": "character", "value": 9}, {"text": "face", "value": 9}], "answer_bag": [{"text": "yes", "value": 304}, {"text": "blue", "value": 162}, {"text": "standing", "value": 93}, {"text": "red", "value": 88}, {"text": "white", "value": 87}, {"text": "green", "value": 82}, {"text": "purple", "value": 81}, {"text": "black", "value": 80}, {"text": "sitting", "value": 75}, {"text": "brown", "value": 44}, {"text": "pink", "value": 43}, {"text": "no", "value": 30}, {"text": "wall", "value": 30}, {"text": "phone", "value": 26}, {"text": "wood", "value": 25}, {"text": "window", "value": 23}, {"text": "building", "value": 20}, {"text": "book", "value": 19}, {"text": "gray", "value": 19}, {"text": "left", "value": 16}, {"text": "tree", "value": 16}, {"text": "chair", "value": 14}, {"text": "floor", "value": 14}, {"text": "object", "value": 14}, {"text": "sign", "value": 14}, {"text": "background", "value": 13}, {"text": "laptop", "value": 13}, {"text": "cup", "value": 12}, {"text": "orange", "value": 12}, {"text": "door", "value": 11}, {"text": "glasses", "value": 11}, {"text": "light", "value": 11}, {"text": "stick", "value": 11}, {"text": "table", "value": 11}, {"text": "toy", "value": 11}, {"text": "blonde", "value": 10}, {"text": "box", "value": 10}, {"text": "cabinet", "value": 10}, {"text": "bag", "value": 9}, {"text": "ground", "value": 9}, {"text": "hat", "value": 9}, {"text": "metal", "value": 9}, {"text": "picture", "value": 9}, {"text": "right", "value": 9}, {"text": "man", "value": 8}, {"text": "mirror", "value": 8}, {"text": "bottle", "value": 7}, {"text": "fence", "value": 7}, {"text": "people", "value": 7}, {"text": "plant", "value": 7}, {"text": "sidewalk", "value": 7}, {"text": "toothbrush", "value": 7}, {"text": "couch", "value": 6}, {"text": "curtain", "value": 6}, {"text": "paper", "value": 6}, {"text": "sky", "value": 6}, {"text": "wheel", "value": 6}, {"text": "woman", "value": 6}, {"text": "bed", "value": 5}, {"text": "dirt", "value": 5}, {"text": "flower", "value": 5}, {"text": "food", "value": 5}, {"text": "microphone", "value": 5}, {"text": "person", "value": 5}, {"text": "plate", "value": 5}, {"text": "rug", "value": 5}, {"text": "television", "value": 5}, {"text": "both", "value": 4}, {"text": "brick", "value": 4}, {"text": "clock", "value": 4}, {"text": "doll", "value": 4}, {"text": "glass", "value": 4}, {"text": "holding", "value": 4}, {"text": "open", "value": 4}, {"text": "outside", "value": 4}, {"text": "pants", "value": 4}, {"text": "pillow", "value": 4}, {"text": "reading", "value": 4}, {"text": "skateboard", "value": 4}, {"text": "tall", "value": 4}, {"text": "umbrella", "value": 4}, {"text": "apron", "value": 3}, {"text": "bedroom", "value": 3}, {"text": "board", "value": 3}, {"text": "camera", "value": 3}, {"text": "cloud", "value": 3}, {"text": "cloudy", "value": 3}, {"text": "crown", "value": 3}, {"text": "dog", "value": 3}, {"text": "eating", "value": 3}, {"text": "eyeglasses", "value": 3}, {"text": "fire", "value": 3}, {"text": "group", "value": 3}, {"text": "kitchen", "value": 3}, {"text": "knife", "value": 3}, {"text": "long", "value": 3}, {"text": "many", "value": 3}, {"text": "microwave", "value": 3}, {"text": "mountain", "value": 3}, {"text": "necklace", "value": 3}], "question_answer_bag": [{"text": "the", "value": 2344}, {"text": "is", "value": 1695}, {"text": "what", "value": 1478}, {"text": "color", "value": 716}, {"text": "man", "value": 505}, {"text": "in", "value": 366}, {"text": "are", "value": 362}, {"text": "on", "value": 357}, {"text": "of", "value": 337}, {"text": "yes", "value": 304}, {"text": "there", "value": 255}, {"text": "person", "value": 254}, {"text": "standing", "value": 210}, {"text": "holding", "value": 185}, {"text": "blue", "value": 170}, {"text": "sitting", "value": 165}, {"text": "woman", "value": 155}, {"text": "shirt", "value": 150}, {"text": "people", "value": 134}, {"text": "wearing", "value": 133}, {"text": "doing", "value": 122}, {"text": "wall", "value": 107}, {"text": "how", "value": 100}, {"text": "many", "value": 97}, {"text": "red", "value": 94}, {"text": "white", "value": 92}, {"text": "green", "value": 89}, {"text": "image", "value": 89}, {"text": "background", "value": 86}, {"text": "behind", "value": 86}, {"text": "purple", "value": 85}, {"text": "black", "value": 84}, {"text": "or", "value": 84}, {"text": "pants", "value": 77}, {"text": "hand", "value": 73}, {"text": "where", "value": 73}, {"text": "hair", "value": 63}, {"text": "left", "value": 60}, {"text": "table", "value": 58}, {"text": "building", "value": 56}, {"text": "front", "value": 55}, {"text": "his", "value": 51}, {"text": "brown", "value": 47}, {"text": "right", "value": 47}, {"text": "door", "value": 46}, {"text": "pink", "value": 46}, {"text": "room", "value": 44}, {"text": "phone", "value": 40}, {"text": "picture", "value": 40}, {"text": "side", "value": 40}, {"text": "window", "value": 40}, {"text": "floor", "value": 39}, {"text": "dress", "value": 35}, {"text": "made", "value": 35}, {"text": "they", "value": 33}, {"text": "chair", "value": 32}, {"text": "jacket", "value": 31}, {"text": "no", "value": 30}, {"text": "other", "value": 29}, {"text": "sign", "value": 29}, {"text": "hat", "value": 27}, {"text": "to", "value": 27}, {"text": "girl", "value": 26}, {"text": "middle", "value": 26}, {"text": "object", "value": 26}, {"text": "tie", "value": 26}, {"text": "tree", "value": 26}, {"text": "at", "value": 25}, {"text": "suit", "value": 25}, {"text": "wood", "value": 25}, {"text": "any", "value": 24}, {"text": "car", "value": 24}, {"text": "ground", "value": 24}, {"text": "mirror", "value": 23}, {"text": "their", "value": 23}, {"text": "book", "value": 21}, {"text": "ceiling", "value": 20}, {"text": "couch", "value": 20}, {"text": "dog", "value": 20}, {"text": "looking", "value": 20}, {"text": "next", "value": 20}, {"text": "can", "value": 19}, {"text": "glasses", "value": 19}, {"text": "gray", "value": 19}, {"text": "boy", "value": 18}, {"text": "sky", "value": 18}, {"text": "you", "value": 18}, {"text": "bed", "value": 17}, {"text": "box", "value": 17}, {"text": "who", "value": 17}, {"text": "chairs", "value": 16}, {"text": "laptop", "value": 16}, {"text": "light", "value": 16}, {"text": "see", "value": 16}, {"text": "toy", "value": 16}, {"text": "bird", "value": 15}, {"text": "cabinet", "value": 14}, {"text": "cap", "value": 14}, {"text": "does", "value": 14}, {"text": "fence", "value": 14}], "category_worker": [{"0 worker": 1381, "1 worker": 706, "name": "incorrect"}, {"0 worker": 1997, "1 worker": 90, "name": "partially incorrect"}, {"2 workers": 1963, "3 workers": 124, "name": "ambiguous"}, {"0 worker": 1762, "1 worker": 325, "name": "partially correct"}, {"0 worker": 1245, "1 worker": 842, "name": "correct"}]}